event_remote/__init__.py
event_remote/event_constants.py
event_remote/event_remote.py
event_remote-0.0.23.dist-info/METADATA
event_remote-0.0.23.dist-info/WHEEL
event_remote-0.0.23.dist-info/top_level.txt
event_remote-0.0.23.dist-info/RECORD
