Metadata-Version: 2.4
Name: event-remote
Version: 0.0.23
Summary: PyPI Package for Circles event-remote Python
Home-page: https://github.com/circles-zone/event-remote-restapi-python-package
Author: Circles
Author-email: info@circlez.ai
Classifier: Programming Language :: Python :: 3
Classifier: License :: Other/Proprietary License
Classifier: Operating System :: OS Independent
Requires-Dist: requests
Requires-Dist: event-external-local>=0.0.21
Requires-Dist: logger-local>=0.0.170
Requires-Dist: python-sdk-remote>=0.0.93
Requires-Dist: url-remote
Requires-Dist: user-context-remote>=0.0.116
Dynamic: author
Dynamic: author-email
Dynamic: classifier
Dynamic: description
Dynamic: description-content-type
Dynamic: home-page
Dynamic: requires-dist
Dynamic: summary
